xlcli/__init__.py
xlcli/main.py
xlcli-0.1.1.dist-info/METADATA
xlcli-0.1.1.dist-info/WHEEL
xlcli-0.1.1.dist-info/entry_points.txt
xlcli-0.1.1.dist-info/licenses/LICENSE
xlcli-0.1.1.dist-info/RECORD
