Metadata-Version: 2.4
Name: xlcli
Version: 0.1.1
Summary: simple Excel Viewer in Terminal
License-File: LICENSE
Requires-Python: >=3.12
Requires-Dist: openpyxl>=3.1.5
Requires-Dist: rich>=13.9.4
Requires-Dist: typer>=0.15.1
